sugartime/__init__.py
sugartime/constants.py
sugartime/core.py
sugartime/model.py
sugartime-0.0.1.dist-info/LICENSE
sugartime-0.0.1.dist-info/METADATA
sugartime-0.0.1.dist-info/WHEEL
sugartime-0.0.1.dist-info/top_level.txt
sugartime-0.0.1.dist-info/RECORD
