Metadata-Version: 2.1
Name: sugartime
Version: 0.0.1
Summary: A python package for modeling and forecasting blood glucose dynamics in diabetics
Home-page: https://github.com/danielkentwood/sugartime
Author: Daniel Wood
Author-email: danielkentwood@gmail.com
License: MIT
Platform: UNKNOWN
Requires-Python: >=3.8
Requires-Dist: numpy
Requires-Dist: scipy
Requires-Dist: scikit-learn
Requires-Dist: pandas
Requires-Dist: fireTS
Requires-Dist: plotly
Requires-Dist: streamlit
